{
  "isApplicationDoc": true,
  "collection": "question",
  "_id": "Household",
  "questions": [

    {
      "_id": "22531",
      "label": "Reason for visiting household",
      "repeatable": "false",
      "id": "22531",
      "radio-options": "Index Case Household, Index Case Neighbors, Mass Screen",
      "type": "radio",
      "action_on_change": "if (ResultOfQuestion('MalariaCaseID') is null and value is 'Mass Screen') then $('[name=MalariaCaseID]').val(moment().format('YYMD') + Math.floor(Math.random()*100000))",

      "repeatable": "false"
    },

    {
      "_id": "531",
      "label": "Malaria Case ID",
      "repeatable": "false",
      "type": "text",
      "id": "531"
    },
    {
      "_id": "401",
      "label": "Head of Household Name",
      "repeatable": "false",
      "type": "autocomplete from previous entries",
      "id": "401"
    },
    {
      "label": "Shehia",
      "id": "398",
      "repeatable": "false",
      "type": "autocomplete from code",
      "autocomplete-options": "window.ShehiaOptions = WardHierarchy.allWards()",
      "validation" : "return 'Shehia is not valid' unless _.contains(window.ShehiaOptions, value)",
      "_id": "398"
    },
    {
      "label": "Village",
      "id": "333",
      "type": "autocomplete from previous entries",
      "repeatable": "false",
      "_id": "333"
    },
    {
      "label": "Sheha/Mjumbe",
      "id": "937",
      "type": "autocomplete from previous entries",
      "repeatable": "false",
      "_id": "937"
    },
    {
      "label": "Contact Mobile # (patient/relative)",
      "id": "363",
      "type": "text",
      "repeatable": "false",
      "_id": "363"
    },
    {
      "_id": "467",
      "label": "Household Location",
      "repeatable": "false",
      "required": "false",
      "type": "location",
      "id": "467"
    },
    {
      "_id": "22467",
      "label": "Followup Neighbors?",
      "repeatable": "false",
      "type": "radio",
      "radio-options": "Yes,No",
      "id": "22467"
    },
    {
      "_id": "22464",
      "label": "Number of other households within 50 steps of index case household",
      "repeatable": "false",
      "type": "number",
      "radio-options": "Yes,No",
      "skip_logic": "ResultOfQuestion('FollowupNeighbors') is 'No'",
      "id": "22464"
    },
    {
      "_id": "618",
      "label": "Total Number of Residents in the Household",
      "repeatable": "false",
      "type": "number",
      "validation" : "return 'Value must be between 0 and 20' if value < 0 or value > 20",
      "id": "618"
    },
    {
      "_id": "771",
      "label": "Number of LLIN",
      "repeatable": "false",
      "type": "number",
      "validation" : "return 'Value must be between 0 and 20' if value < 0 or value > 20",
      "id": "771"
    },
    {
      "_id": "233",
      "label": "Number of Sleeping Places (beds/mattresses)",
      "repeatable": "false",
      "type": "number",
      "validation" : "return 'Value must be between 0 and 20' if value < 0 or value > 20",
      "id": "233"
    },


    {
      "_id": "7233",
      "label": "Have you given coupon(s) for nets",
      "radio-options": "Yes,No",
      "repeatable": "false",
      "type": "radio",
      "skip_logic": "console.log ResultOfQuestion('NumberofLLIN');ResultOfQuestion('NumberofLLIN') >= ResultOfQuestion('NumberofSleepingPlacesbedsmattresses')",
      "id": "7233"
    },
    {
      "_id": "8233",
      "label": "Coupon Numbers",
      "repeatable": "false",
      "type": "text",
      "required": "false",
      "skip_logic": "ResultOfQuestion('Haveyougivencouponsfornets') is null or ResultOfQuestion('Haveyougivencouponsfornets') is 'No' ",
      "id": "8233"
    },



    {
      "_id": "625",
      "label": "Number of Household Members with Fever or History of Fever Within Past Week",
      "repeatable": "false",
      "type": "number",
      "validation" : "return 'Value must be between 0 and 20' if value < 0 or value > 20",
      "id": "625"
    },
    {
      "_id": "305",
      "label": "Number of Household Members Treated for Malaria Within Past Week",
      "repeatable": "false",
      "type": "number",
      "validation" : "return 'Value must be between 0 and 20' if value < 0 or value > 20",
      "id": "305"
    },
    {
      "_id": "105",
      "radio-options": "Yes,No,Unknown,Not Applicable",
      "label": "Index case: If patient is female 15-45 years of age, is she is pregant?",
      "repeatable": "false",
      "type": "radio",
      "id": "105"
    },
    {
      "label": "Index case: Patient's current status",
      "id": "768",
      "radio-options": "Feeling Better, Feeling Unchanged, Feeling Worse, Admitted, Died ",
      "type": "radio",
      "repeatable": "false",
      "_id": "768"
    },
    {
      "label": "Index case: Patient's treatment status",
      "id": "168",
      "radio-options": "Completed, In Progress, Stopped",
      "type": "radio",
      "repeatable": "false",
      "_id": "768"
    },
    {
      "label": "Index case: Slept under LLIN last night?",
      "id": "728",
      "radio-options": "Yes,No,Unknown,Not Applicable",
      "type": "radio",
      "repeatable": "false",
      "_id": "768"
    },
    {
      "_id": "755",
      "label": "Last date of IRS",
      "repeatable": "false",
      "type": "date",
      "id": "755"
    },
    {
      "id": "341",
      "_id": "341",
      "label": "complete",
      "type": "checkbox",
      "repeatable": "false"
    }
  ],
  "resultSummaryFields": {
    "Head of Household Name": "on",
    "Total Number of Residents in the Household": "on",
    "Malaria Case ID": "on"
  },
  "id": "Household"
}
